dectate/__init__.py
dectate/app.py
dectate/config.py
dectate/error.py
dectate/query.py
dectate/sentinel.py
dectate/sphinxext.py
dectate/tool.py
dectate/toposort.py
dectate/tests/__init__.py
dectate/tests/test_directive.py
dectate/tests/test_error.py
dectate/tests/test_helpers.py
dectate/tests/test_logging.py
dectate/tests/test_query.py
dectate/tests/test_sentinel.py
dectate/tests/test_tool.py
dectate/tests/test_toposort.py
dectate/tests/fixtures/__init__.py
dectate/tests/fixtures/anapp.py
dectate-0.14.dist-info/LICENSE.txt
dectate-0.14.dist-info/METADATA
dectate-0.14.dist-info/WHEEL
dectate-0.14.dist-info/top_level.txt
dectate-0.14.dist-info/RECORD
