Metadata-Version: 2.1
Name: dectate
Version: 0.14
Summary: A configuration engine for Python frameworks
Home-page: http://dectate.readthedocs.io
Author: Martijn Faassen
Author-email: faassen@startifact.com
License: BSD
Keywords: configuration
Platform: UNKNOWN
Classifier: Intended Audience :: Developers
Classifier: License :: OSI Approved :: BSD License
Classifier: Topic :: Software Development :: Libraries :: Application Frameworks
Classifier: Programming Language :: Python :: 3.4
Classifier: Programming Language :: Python :: 3.5
Classifier: Programming Language :: Python :: 3.6
Classifier: Programming Language :: Python :: 3.7
Classifier: Programming Language :: Python :: 3.8
Classifier: Programming Language :: Python :: Implementation :: PyPy
Classifier: Development Status :: 5 - Production/Stable
Provides-Extra: test
Provides-Extra: coverage
Provides-Extra: pep8
Provides-Extra: docs
